ruptures/__init__.py
ruptures/base.py
ruptures/exceptions.py
ruptures/version.py
ruptures/costs/__init__.py
ruptures/costs/costautoregressive.py
ruptures/costs/costclinear.py
ruptures/costs/costcosine.py
ruptures/costs/costl1.py
ruptures/costs/costl2.py
ruptures/costs/costlinear.py
ruptures/costs/costml.py
ruptures/costs/costnormal.py
ruptures/costs/costrank.py
ruptures/costs/costrbf.py
ruptures/costs/factory.py
ruptures/datasets/__init__.py
ruptures/datasets/pw_constant.py
ruptures/datasets/pw_linear.py
ruptures/datasets/pw_normal.py
ruptures/datasets/pw_wavy.py
ruptures/detection/__init__.py
ruptures/detection/binseg.py
ruptures/detection/bottomup.py
ruptures/detection/dynp.py
ruptures/detection/kernelcpd.py
ruptures/detection/pelt.py
ruptures/detection/window.py
ruptures/detection/_detection/__init__.py
ruptures/detection/_detection/ekcpd.c
ruptures/detection/_detection/ekcpd.cpython-311-aarch64-linux-gnu.so
ruptures/detection/_detection/ekcpd.pxd
ruptures/detection/_detection/ekcpd.pyx
ruptures/detection/_detection/ekcpd_computation.c
ruptures/detection/_detection/ekcpd_computation.h
ruptures/detection/_detection/ekcpd_pelt_computation.c
ruptures/detection/_detection/ekcpd_pelt_computation.h
ruptures/detection/_detection/kernels.c
ruptures/detection/_detection/kernels.h
ruptures/metrics/__init__.py
ruptures/metrics/hamming.py
ruptures/metrics/hausdorff.py
ruptures/metrics/precisionrecall.py
ruptures/metrics/randindex.py
ruptures/metrics/sanity_check.py
ruptures/metrics/timeerror.py
ruptures/show/__init__.py
ruptures/show/display.py
ruptures/utils/__init__.py
ruptures/utils/bnode.py
ruptures/utils/drawbkps.py
ruptures/utils/utils.py
ruptures/utils/_utils/__init__.py
ruptures/utils/_utils/convert_path_matrix.c
ruptures/utils/_utils/convert_path_matrix.cpython-311-aarch64-linux-gnu.so
ruptures/utils/_utils/convert_path_matrix.pxd
ruptures/utils/_utils/convert_path_matrix.pyx
ruptures-1.1.10.dist-info/METADATA
ruptures-1.1.10.dist-info/WHEEL
ruptures-1.1.10.dist-info/top_level.txt
ruptures-1.1.10.dist-info/zip-safe
ruptures-1.1.10.dist-info/RECORD
ruptures-1.1.10.dist-info/licenses/LICENSE
