Metadata-Version: 2.4
Name: ruptures
Version: 1.1.10
Summary: Change point detection for signals in Python.
Home-page: https://github.com/deepcharles/ruptures/
Author: Charles Truong, Laurent Oudre, Nicolas Vayatis
Author-email: charles@doffy.net
Maintainer: Charles Truong, Olivier Boulant
License: BSD-2-Clause
Project-URL: Documentation, https://centre-borelli.github.io/ruptures-docs/
Project-URL: Source, https://github.com/deepcharles/ruptures/
Project-URL: Bug Tracker, https://github.com/deepcharles/ruptures/issues/
Keywords: change point detection,signal segmentation,computer science,machine learning,kernel methods,time series
Classifier: Programming Language :: Python :: 3
Classifier: Operating System :: OS Independent
Classifier: Topic :: Scientific/Engineering :: Mathematics
Classifier: Intended Audience :: Science/Research
Classifier: License :: OSI Approved :: BSD License
Requires-Python: <3.14,>=3.9
License-File: LICENSE
Requires-Dist: numpy
Requires-Dist: scipy
Provides-Extra: display
Requires-Dist: matplotlib; extra == "display"
Provides-Extra: test
Requires-Dist: pytest; extra == "test"
Requires-Dist: pytest-cov; extra == "test"
Provides-Extra: dev
Requires-Dist: pre-commit; extra == "dev"
Provides-Extra: docs
Requires-Dist: jupyter; extra == "docs"
Requires-Dist: librosa; extra == "docs"
Requires-Dist: matplotlib; extra == "docs"
Requires-Dist: mkdocs; extra == "docs"
Requires-Dist: mkdocs-macros-plugin; extra == "docs"
Requires-Dist: mkdocs-material; extra == "docs"
Requires-Dist: mkdocs-section-index; extra == "docs"
Requires-Dist: mkdocstrings[python]>=0.18; extra == "docs"
Requires-Dist: mknotebooks; extra == "docs"
Requires-Dist: pymdown-extensions; extra == "docs"
Requires-Dist: nltk; extra == "docs"
Dynamic: license-file
